scaleup/__init__.py
scaleup/check_data.py
scaleup/dynochem_automation.py
scaleup/dynochem_automation_defs.py
scaleup/scaleup.py
scaleup/script_utils.py
scaleup/scripts.py
scaleup/excel/__init__.py
scaleup/excel/excel_utils.py
scaleup/tests/__init__.py
scaleup/tests/script_utils_test.py
scaleup-1.0.27.dist-info/LICENSE
scaleup-1.0.27.dist-info/METADATA
scaleup-1.0.27.dist-info/WHEEL
scaleup-1.0.27.dist-info/top_level.txt
scaleup-1.0.27.dist-info/RECORD
