Metadata-Version: 2.1
Name: scaleup
Version: 1.0.27
Summary: Python scripting library for Scale-up RunScript Automation
Home-page: UNKNOWN
Author: Scale-up Systems
Author-email: python.support@scale-up.com
License: UNKNOWN
Platform: UNKNOWN
Classifier: Programming Language :: Python :: 3
Classifier: License :: OSI Approved :: MIT License
Classifier: Operating System :: Microsoft :: Windows
Requires-Python: >=3.6
License-File: LICENSE
Requires-Dist: pandas
Requires-Dist: pywin32
Requires-Dist: openpyxl
